[
    {
        "task_id": "T01",
        "answer": "Timeout Error"
    },
    {
        "task_id": "T01b",
        "answer": "Timeout Error"
    },
    {
        "task_id": "T01c",
        "answer": "Timeout Error"
    },
    {
        "task_id": "T02",
        "answer": "Timeout Error"
    },
    {
        "task_id": "T02b",
        "answer": "Timeout Error"
    },
    {
        "task_id": "T03",
        "answer": "Timeout Error"
    },
    {
        "task_id": "T03b",
        "answer": "Timeout Error"
    },
    {
        "task_id": "T04",
        "answer": "Timeout Error"
    },
    {
        "task_id": "T04b",
        "answer": "Timeout Error"
    },
    {
        "task_id": "T05",
        "answer": "Timeout Error"
    }
]